wifi/__init__.py
wifi/__main__.py
wifi/cli.py
wifi/exceptions.py
wifi/scan.py
wifi/scheme.py
wifi/subprocess_compat.py
wifi/utils.py
wifi-0.8.0rc1.dist-info/DESCRIPTION.rst
wifi-0.8.0rc1.dist-info/METADATA
wifi-0.8.0rc1.dist-info/RECORD
wifi-0.8.0rc1.dist-info/WHEEL
wifi-0.8.0rc1.dist-info/entry_points.txt
wifi-0.8.0rc1.dist-info/metadata.json
wifi-0.8.0rc1.dist-info/top_level.txt
