Metadata-Version: 2.0
Name: wifi
Version: 0.8.0rc1
Summary: 
Requires-Dist: pbkdf2
Requires-Dist: setuptools
